aparse/__init__.py
aparse/_handlers.py
aparse/_lib.py
aparse/argparse.py
aparse/click.py
aparse/core.py
aparse/utils.py
aparse-0.0.19.dist-info/LICENSE
aparse-0.0.19.dist-info/METADATA
aparse-0.0.19.dist-info/WHEEL
aparse-0.0.19.dist-info/top_level.txt
aparse-0.0.19.dist-info/RECORD
