Metadata-Version: 2.1
Name: aparse
Version: 0.0.19
Author: Jonáš Kulhánek
Author-email: jonas.kulhanek@live.com
License: MIT License
Requires-Python: >=3.7
License-File: LICENSE
